jhu_primitives/__init__.py
jhu_primitives/jupyter_notebook_config.py
jhu_primitives/sperf.py
jhu_primitives/adj_concat/__init__.py
jhu_primitives/adj_concat/adj_concat.py
jhu_primitives/ase/__init__.py
jhu_primitives/ase/ase.R
jhu_primitives/ase/ase.interface.R
jhu_primitives/ase/ase.py
jhu_primitives/dimselect/__init__.py
jhu_primitives/dimselect/dimselect.R
jhu_primitives/dimselect/dimselect.interface.R
jhu_primitives/dimselect/dimselect.py
jhu_primitives/dimselect/getElbows.R
jhu_primitives/dimselect/profile_likelihood_maximization.py
jhu_primitives/gclass/__init__.py
jhu_primitives/gclass/gclass.py
jhu_primitives/gclust/__init__.py
jhu_primitives/gclust/gclust.R
jhu_primitives/gclust/gclust.interface.R
jhu_primitives/gclust/gclust.py
jhu_primitives/lcc/__init__.py
jhu_primitives/lcc/lcc.py
jhu_primitives/link_pred_graph_reader/__init__.py
jhu_primitives/link_pred_graph_reader/link_pred_graph_reader.py
jhu_primitives/link_pred_rc/__init__.py
jhu_primitives/link_pred_rc/link_pred_rc.py
jhu_primitives/load_graphs/__init__.py
jhu_primitives/load_graphs/load_graphs.py
jhu_primitives/lse/__init__.py
jhu_primitives/lse/lse.R
jhu_primitives/lse/lse.interface.R
jhu_primitives/lse/lse.py
jhu_primitives/nonpar/__init__.py
jhu_primitives/nonpar/nonpar.R
jhu_primitives/nonpar/nonpar.interface.R
jhu_primitives/nonpar/nonpar.py
jhu_primitives/numclust/__init__.py
jhu_primitives/numclust/numclust.R
jhu_primitives/numclust/numclust.interface.R
jhu_primitives/numclust/numclust.py
jhu_primitives/oocase/__init__.py
jhu_primitives/oocase/oocase.R
jhu_primitives/oocase/oocase.interface.R
jhu_primitives/oocase/oocase.py
jhu_primitives/ptr/__init__.py
jhu_primitives/ptr/passtoranks.R
jhu_primitives/ptr/ptr.R
jhu_primitives/ptr/ptr.interface.R
jhu_primitives/ptr/ptr.py
jhu_primitives/sgc/__init__.py
jhu_primitives/sgc/sgc.R
jhu_primitives/sgc/sgc.interface.R
jhu_primitives/sgc/sgc.py
jhu_primitives/sgm/__init__.py
jhu_primitives-2020.1.9.1.dist-info/DESCRIPTION.rst
jhu_primitives-2020.1.9.1.dist-info/METADATA
jhu_primitives-2020.1.9.1.dist-info/RECORD
jhu_primitives-2020.1.9.1.dist-info/WHEEL
jhu_primitives-2020.1.9.1.dist-info/dependency_links.txt
jhu_primitives-2020.1.9.1.dist-info/entry_points.txt
jhu_primitives-2020.1.9.1.dist-info/metadata.json
jhu_primitives-2020.1.9.1.dist-info/top_level.txt
